23-24Spring/计算机组成/Lab/Lab4/Lab4/SCPU/SCPU.srcs/sources_1/imports/COLab/SCPU/SCPU.srcs/sources_1/new/Controller.v
`timescale 1ns / 1ps

module Controller(
    input [4:0]       OPcode, 
    input [2:0]       Fun3,
    input             Fun7,

    output reg [1:0]  Jump,         // 选择 PC 的下一个值，0 为 PC+4，1 为 J-Type，2 为 Jalr 目标地址
    output reg        RegWrite,     // 选择是否写回寄存器，0 不写回，1 写回 
    output reg        ALUSrc_B,     // 选择 ALU 的 B 输入口，0 寄存器值，1 立即数
    output reg [1:0]  Store_len,    // 选择 Store 指令的数据存储长度，0 sb，1 sh，2 sw
    output reg [3:0]  ALU_Control,  // 选择 ALU 的运算方式 
    output reg [2:0]  MemtoReg,     // 选择写回寄存器的数据来源，0 ALU 输出，1 内存读出的值，2 PC+4，3 lui，4 auipc
    output reg [3:0]  MemRW,        // 选择内存的读写方式，0 为读，1 为写，共 4byte
    output reg [2:0]  Load_len,     // 选择 Load 指令的数据读取长度，并进行符号位扩展，000 lb，010 lh，100 lw，001 lbu，011 lhu
    output reg        Branch,       // Beq指令选择是否进行分支跳转，0 不跳转，1 跳转
    output reg        BranchN       // Bne指令选择是否进行分支跳转，0 不跳转，1 跳转
);

    always @(*) begin
        // R-type
        if(OPcode == 5'b01100) begin
            Jump = 0;
            RegWrite = 1;
            ALUSrc_B = 0;
            MemtoReg = 0;
            MemRW = 0;
            Branch = 0;
            BranchN = 0;
            case(Fun3)
                3'b000: begin       // add sub
                    if(~Fun7) 
                        ALU_Control = 4'b0000;
                    else
                        ALU_Control = 4'b0001;
                end
                3'b001: begin       // sll
                        ALU_Control = 4'b0010;
                end
                3'b010: begin       // slt
                        ALU_Control = 4'b0011;
                end
                3'b011: begin       // sltu
                        ALU_Control = 4'b0100;
                end
                3'b100: begin       // xor
                        ALU_Control = 4'b0101;
                end
                3'b101: begin       // srl sra
                    if(~Fun7)
                        ALU_Control = 4'b0110;
                    else
                        ALU_Control = 4'b0111;
                end
                3'b110: begin       // or
                        ALU_Control = 4'b1000;
                end
                3'b111: begin       // and
                        ALU_Control = 4'b1001;
                end
            endcase
        end

        // I-type 1
        if(OPcode == 5'b00100) begin
            Jump = 0;
            RegWrite = 1;
            ALUSrc_B = 1;
            MemtoReg = 0;
            MemRW = 0;
            Branch = 0;
            BranchN = 0;
            case(Fun3)
                3'b000: begin       // addi
                        ALU_Control = 4'b0000;
                end
                3'b010: begin       // slti
                        ALU_Control = 4'b0011;
                end
                3'b011: begin       // sltiu
                        ALU_Control = 4'b0100;
                end
                3'b100: begin       // xori
                        ALU_Control = 4'b0101;
                end
                3'b110: begin       // ori
                        ALU_Control = 4'b1000;
                end
                3'b111: begin       // andi
                        ALU_Control = 4'b1001;
                end
                3'b001: begin       // slli
                        ALU_Control = 4'b0010;
                end
                3'b101: begin       // srli srai
                    if(~Fun7)
                        ALU_Control = 4'b0110;
                    else
                        ALU_Control = 4'b0111;
                end
            endcase
        end

        // I-type 2
        if(OPcode == 5'b00000) begin
            Jump = 0;
            RegWrite = 1;
            ALUSrc_B = 1;
            ALU_Control = 4'b0000;
            MemtoReg = 3'b001;
            MemRW = 0;
            Branch = 0;
            BranchN = 0;
            case(Fun3)
                3'b000: begin       // lb
                        Load_len = 3'b000;
                end
                3'b001: begin       // lh
                        Load_len = 3'b010;
                end
                3'b010: begin       // lw
                        Load_len = 3'b100;
                end
                3'b100: begin       // lbu
                        Load_len = 3'b001;
                end
                3'b101: begin       // lhu
                        Load_len = 3'b011;
                end
            endcase
        end

        // I-type 3
        if(OPcode == 5'b11001) begin    // jalr
            Jump = 2'b10;
            RegWrite = 1;
            ALUSrc_B = 1;
            ALU_Control = 4'b0000;
            MemtoReg = 3'b010;
        end

        // S-type
        if(OPcode == 5'b01000) begin
            Jump = 2'b000;
            RegWrite = 0;
            ALUSrc_B = 1;
            ALU_Control = 4'b0000;
            MemRW = 4'b1111;
            Branch = 0;
            BranchN = 0;
            case(Fun3)
                3'b000: begin           // sb    
                        Store_len = 2'b00;
                end
                3'b001: begin           // sh
                        Store_len = 2'b01;
                end
                3'b010: begin           // sw
                        Store_len = 2'b10;
                end
            endcase
        end

        // B-type
        if(OPcode == 5'b11000) begin
            Jump = 0;
            RegWrite = 0;
            ALUSrc_B = 0;
            case(Fun3)
                3'b000: begin           // beq
                        ALU_Control = 4'b0001;
                        Branch = 1;
                        BranchN = 0;
                end
                3'b001: begin           // bne
                        ALU_Control = 4'b0001;
                        Branch = 0;
                        BranchN = 1;
                end
                3'b100: begin           // blt
                        ALU_Control = 4'b0011;
                        Branch = 0;
                        BranchN = 1;
                end
                3'b101: begin           // bge
                        ALU_Control = 4'b0011;
                        Branch = 1;
                        BranchN = 0;
                end
                3'b110: begin           // bltu
                        ALU_Control = 4'b0100;
                        Branch = 0;
                        BranchN = 1;
                end
                3'b111: begin           // bgeu
                        ALU_Control = 4'b0100;
                        Branch = 1;
                        BranchN = 0;
                end
            endcase
        end

        // U-type 1
        if(OPcode == 5'b01101) begin    // lui
            Jump = 0;
            RegWrite = 1;
            MemtoReg = 3'b011;
            Branch = 0;
            BranchN = 0;
        end

        // U-type 2
        if(OPcode == 5'b00101) begin    // auipc
            Jump = 0;
            RegWrite = 1;
            MemtoReg = 3'b100;
            Branch = 0;
            BranchN = 0;
        end

        // J-type
        if(OPcode == 5'b11011) begin    // jal
            Jump = 1;
            RegWrite = 1;
            MemtoReg = 3'b010;
            Branch = 0;
            BranchN = 0;
        end
    end

endmodule

23-24Spring/计算机组成/Lab/Lab4/Lab4-4/SCPU/SCPU.srcs/sim_1/imports/new/Controller_tb.v
`timescale 1ns / 1ps

module Controller_tb();
  reg [4:0]     OPcode;
  reg [2:0]     Fun3;
  reg           Fun7;

  wire [1:0]    Jump;
  wire          RegWrite;
  wire          ALUSrc_B;
  wire [1:0]    Store_len;
  wire [3:0]    ALU_Control;
  wire [2:0]    MemtoReg;
  wire          MemRW;
  wire [2:0]    Load_len;
  wire          Branch;
  wire          BranchN;
  
Controller m0(
    .OPcode(OPcode),
    .Fun3(Fun3),
    .Fun7(Fun7),

    .Jump(Jump),
    .RegWrite(RegWrite),
    .ALUSrc_B(ALUSrc_B),
    .Store_len(Store_len),
    .ALU_Control(ALU_Control),
    .MemtoReg(MemtoReg),
    .MemRW(MemRW),
    .Load_len(Load_len),
    .Branch(Branch),
    .BranchN(BranchN)
	);

  reg [31:0] inst_for_test;

`define LET_INST_BE(inst) \
  inst_for_test = inst; \
  OPcode = inst_for_test[6:2]; \
  Fun3 = inst_for_test[14:12]; \
  Fun7 = inst_for_test[30]; \
  #5;

  initial begin
    $dumpfile("Controller.vcd");
    $dumpvars(1, Controller_tb);

    #5;
    // R-type
    `LET_INST_BE(32'h001100B3);   //add x1, x2, x1
    `LET_INST_BE(32'h400080B3);   //sub x1, x1, x0
    `LET_INST_BE(32'h002140B3);   //xor x1, x2, x2
    `LET_INST_BE(32'h002160B3);   //or x1, x2, x2
    `LET_INST_BE(32'h002170B3);   //and x1, x2, x2
    `LET_INST_BE(32'h002110B3);   //sll x1, x2, x2
    `LET_INST_BE(32'h002150B3);   //srl x1, x2, x2
    `LET_INST_BE(32'h402150B3);   //sra x1, x2, x2
    `LET_INST_BE(32'h002120B3);   //slt x1, x2, x2
    `LET_INST_BE(32'h002130B3);   //sltu x1, x2, x2
    #5;
    // I-type
    `LET_INST_BE(32'h3E810093);   //addi x1, x2, 1000
    `LET_INST_BE(32'h00A14093);   //xori x1, x2, 10
    `LET_INST_BE(32'h00116093);   //ori x1, x2, 1
    `LET_INST_BE(32'h00017093);   //andi x1, x2, 0
    `LET_INST_BE(32'h00011093);   //slli x1, x2, 0
    `LET_INST_BE(32'h00515093);   //srli x1, x2, 5
    `LET_INST_BE(32'h40515093);   //srai x1, x2, 5
    `LET_INST_BE(32'hFFF12093);   //slti x1, x2, -1
    `LET_INST_BE(32'hFFF13093);   //sltiu x1, x2, -1
    #5;
    // Load and store
    `LET_INST_BE(32'h00812083);   //lw x1, 8(x2)
    `LET_INST_BE(32'h00A11083);   //lh x1, 10(x2)
    `LET_INST_BE(32'h00C10083);   //lb x1, 12(x2)
    `LET_INST_BE(32'h01A15083);   //lhu x1, 26(x2)
    `LET_INST_BE(32'h01C14083);   //lbu x1, 28(x2)
    
    `LET_INST_BE(32'h00C0A823);   //sw x12, 16(x1)
    `LET_INST_BE(32'h00111723);   //sh x12, 14(x1)
    `LET_INST_BE(32'h00110923);   //sb x12, 18(x1)
    #5;
    // B-type
    `LET_INST_BE(32'h00108563);   //beq x1, x1, 10
    `LET_INST_BE(32'h00109663);   //bne x1, x1, 12
    `LET_INST_BE(32'h0010C763);   //blt x1, x1, 14
    `LET_INST_BE(32'h0010D863);   //bge x1, x1, 16
    `LET_INST_BE(32'h0010E963);   //bltu x1, x1, 18
    `LET_INST_BE(32'h0010FA63);   //bgeu x1, x1, 20
    #5;
    // J-type
    `LET_INST_BE(32'hF9DFF06F);   //jal x0, -100
    #5;
    // jalr
    `LET_INST_BE(32'h3FF100E7);   //jalr x1, x2, 1020
    #5;
    // lui
    `LET_INST_BE(32'h003FF0B7);   //lui x1, 1018
    #5;
    // auipc
    `LET_INST_BE(32'h003FF097);   //auipc x1, 1016


    #50; $finish();
  end
endmodule

23-24Spring/计算机组成/Lab/Lab4/Lab4/SCPU/SCPU.sim/sim_1/behav/xsim/Controller.vcd
$date
   Sat Apr 27 19:05:37 2024
$end

$version
  2023.2
  $dumpfile ("Controller.vcd") 
$end

$timescale
  1ps
$end

$scope module Controller_tb $end
$var reg 5 ! OPcode [4:0] $end
$var reg 3 " Fun3 [2:0] $end
$var reg 1 # Fun7 $end
$var wire 2 $ Jump [1:0] $end
$var wire 1 % RegWrite $end
$var wire 1 & ALUSrc_B $end
$var wire 2 ' Store_len [1:0] $end
$var wire 4 ( ALU_Control [3:0] $end
$var wire 3 ) MemtoReg [2:0] $end
$var wire 1 * MemRW $end
$var wire 3 + Load_len [2:0] $end
$var wire 1 , Branch $end
$var wire 1 - BranchN $end
$var reg 32 . inst_for_test [31:0] $end
$upscope $end
$scope module glbl $end
$upscope $end
$enddefinitions $end

#0
$dumpvars
bx !
bx "
x#
bx $
x%
x&
bx '
bx (
bx )
x*
bx +
x,
x-
bx .
$end

#5000
b1100 !
b0 "
0#
b0 $
1%
0&
b0 (
b0 )
0*
0,
0-
b100010000000010110011 .

#10000
1#
b1 (
b1000000000000001000000010110011 .

#15000
b100 "
0#
b101 (
b1000010100000010110011 .

#20000
b110 "
b1000 (
b1000010110000010110011 .

#25000
b111 "
b1001 (
b1000010111000010110011 .

#30000
b1 "
b10 (
b1000010001000010110011 .

#35000
b101 "
b110 (
b1000010101000010110011 .

#40000
1#
b111 (
b1000000001000010101000010110011 .

#45000
b10 "
0#
b11 (
b1000010010000010110011 .

#50000
b11 "
b100 (
b1000010011000010110011 .

#60000
b100 !
b0 "
1&
b0 (
b111110100000010000000010010011 .

#65000
b100 "
b101 (
b101000010100000010010011 .

#70000
b110 "
b1000 (
b100010110000010010011 .

#75000
b111 "
b1001 (
b10111000010010011 .

#80000
b1 "
b10 (
b10001000010010011 .

#85000
b101 "
b110 (
b10100010101000010010011 .

#90000
1#
b111 (
b1000000010100010101000010010011 .

#95000
b10 "
b11 (
b11111111111100010010000010010011 .

#100000
b11 "
b100 (
b11111111111100010011000010010011 .

#110000
b0 !
b10 "
0#
b0 (
b1 )
b100 +
b100000010010000010000011 .

#115000
b1 "
b10 +
b101000010001000010000011 .

#120000
b0 "
b0 +
b110000010000000010000011 .

#125000
b101 "
b11 +
b1101000010101000010000011 .

#130000
b100 "
b1 +
b1110000010100000010000011 .

#135000
b1000 !
b10 "
0%
b10 '
1*
b110000001010100000100011 .

#140000
b1 "
b1 '
b100010001011100100011 .

#145000
b0 "
b0 '
b100010000100100100011 .

#155000
b11000 !
0&
b1 (
1,
b100001000010101100011 .

#160000
b1 "
0,
1-
b100001001011001100011 .

#165000
b100 "
b11 (
b100001100011101100011 .

#170000
b101 "
1,
0-
b100001101100001100011 .

#175000
b110 "
b100 (
0,
1-
b100001110100101100011 .

#180000
b111 "
1,
0-
b100001111101001100011 .

#190000
b11011 !
1#
b1 $
1%
b10 )
0,
b11111001110111111111000001101111 .

#200000
b11001 !
b0 "
0#
b10 $
1&
b0 (
b111111111100010000000011100111 .

#210000
b1101 !
b111 "
b0 $
b11 )
b1111111111000010110111 .

#220000
b101 !
b100 )
b1111111111000010010111 .
