23-24Spring/计算机组成/Lab/Lab4/Lab4/SCPU/SCPU.srcs/sources_1/imports/COLab/SCPU/SCPU.srcs/sources_1/new/ImmG.v
`timescale 1ns / 1ps

module ImmG(
    input [31:0]        inst_imm,

    output reg [31:0]   Imm_out
    );

    always @(*) begin
        case(inst_imm[6:2])
            5'b00100: begin                                 // I_type1
                if(inst_imm[14:12] == 3'b001 | inst_imm[14:12] == 3'b101)   // slli srli srai
                        Imm_out = {27'b0,inst_imm[24:20]};
                else
                    if(inst_imm[31] == 1)
                        Imm_out = {20'hF_FFFF,inst_imm[31:20]};
                    else
                        Imm_out = {20'b0,inst_imm[31:20]};
            end
            5'b00000: begin                                  // I_type2
                if(inst_imm[31] == 1)
                    Imm_out = {20'hF_FFFF,inst_imm[31:20]};       
                else
                    Imm_out = {20'b0,inst_imm[31:20]};     
            end
            5'b11001: begin                                  // I_type3
                if(inst_imm[31] == 1)
                    Imm_out = {20'hF_FFFF,inst_imm[31:20]};       
                else
                    Imm_out = {20'b0,inst_imm[31:20]};      
            end
            5'b01000: begin                                  // S_type
                if(inst_imm[31] == 1)
                    Imm_out = {20'hF_FFFF,inst_imm[31:25],inst_imm[11:7]};   
                else
                    Imm_out = {20'b0,inst_imm[31:25],inst_imm[11:7]}; 
            end
            5'b11000: begin                                  // B_type
                if(inst_imm[31] == 1)
                    Imm_out = {20'hF_FFFF,inst_imm[31],inst_imm[7],inst_imm[30:25],inst_imm[11:8],1'b0}; 
                else
                    Imm_out = {20'b0,inst_imm[31],inst_imm[7],inst_imm[30:25],inst_imm[11:8],1'b0}; 
            end
            5'b01101: begin                                  // U_type lui
                    Imm_out = {inst_imm[31:12],12'b0}; 
            end
            5'b00101: begin                                  // U_type auipc
                    Imm_out = {inst_imm[31:12],12'b0};
            end
            5'b11011: begin                                  // J_type
                if(inst_imm[31] == 1)
                    Imm_out = {12'hFFF,inst_imm[31],inst_imm[19:12],inst_imm[20],inst_imm[30:21],1'b0};
                else
                    Imm_out = {12'b0,inst_imm[31],inst_imm[19:12],inst_imm[20],inst_imm[30:21],1'b0};
            end
        endcase
    end
endmodule

23-24Spring/计算机组成/Lab/Lab4/Lab4-4/SCPU/SCPU.srcs/sim_1/imports/new/ImmG_tb.v
`timescale 1ns/1ps
module ImmG_tb();
  reg [31:0]  inst_imm;
  wire[31:0]  Imm_out;

  ImmG m0 (.inst_imm(inst_imm), .Imm_out(Imm_out));

`define LET_INST_BE(inst) \
  inst_imm = inst; \
  #5;

  initial begin
    $dumpfile("ImmG.vcd");
    $dumpvars(1, ImmG_tb);

    #5;
    // Test for I-Type
    `LET_INST_BE(32'h3E810093);   //addi x1, x2, 1000
    `LET_INST_BE(32'h00A14093);   //xori x1, x2, 10
    `LET_INST_BE(32'h00116093);   //ori x1, x2, 1
    `LET_INST_BE(32'h00017093);   //andi x1, x2, 0
    `LET_INST_BE(32'h01411093);   //slli x1, x2, 20
    `LET_INST_BE(32'h00515093);   //srli x1, x2, 5
    `LET_INST_BE(32'h41815093);   //srai x1, x2, 24
    `LET_INST_BE(32'hFFF12093);   //slti x1, x2, -1
    `LET_INST_BE(32'h3FF13093);   //sltiu x1, x2, 1023
    `LET_INST_BE(32'h0E910083);   //lb x1, 233(x2)

    #20;
    // Test for S-Type
    `LET_INST_BE(32'hFE110DA3);   //sb x1, -5(x2)
    `LET_INST_BE(32'h00211023);   //sh x2, 0(x2)
    `LET_INST_BE(32'h00C0A523);   //sw x12, 10(x1)

    #20;
    // Test for B-Type
    `LET_INST_BE(32'hFE108AE3);   //beq x1, x1, -12
    `LET_INST_BE(32'h00211463);   //bne x2, x2, 8
    `LET_INST_BE(32'h0031CA63);   //blt x3, x3, 20
    `LET_INST_BE(32'hFE4256E3);   //bge x4, x4, -20

    #20;
    // Test for J-Type
    `LET_INST_BE(32'hF9DFF06F);   //jal x0, -100
    `LET_INST_BE(32'h3FE000EF);   //jal x1, 1023 NOTE: does ImmGen output 1023?

    #20;
    // Test for jalr
    `LET_INST_BE(32'h3FE280E7);   // jalr x1, x5, 1022
    `LET_INST_BE(32'hC02280E7);   // jalr x1, x5, -1022

    #20;
    // Test for lui auipc 
    `LET_INST_BE(32'h003D0A37);    // lui x19, 976
    `LET_INST_BE(32'h800009B7);    // lui x19, 524288
    `LET_INST_BE(32'h003D0A17);    // auipc x19, 976
    `LET_INST_BE(32'h80000997);    // auipc x19, 524288

    #50; $finish();
  end
endmodule

23-24Spring/计算机组成/Lab/Lab4/Lab4/SCPU/SCPU.sim/sim_1/behav/xsim/ImmG.vcd
$date
   Sat Apr 27 19:26:16 2024
$end

$version
  2023.2
  $dumpfile ("ImmG.vcd") 
$end

$timescale
  1ps
$end

$scope module ImmG_tb $end
$var reg 32 ! inst_imm [31:0] $end
$var wire 32 " Imm_out [31:0] $end
$upscope $end
$scope module glbl $end
$upscope $end
$enddefinitions $end

#0
$dumpvars
bx !
bx "
$end

#5000
b111110100000010000000010010011 !
b1111101000 "

#10000
b101000010100000010010011 !
b1010 "

#15000
b100010110000010010011 !
b1 "

#20000
b10111000010010011 !
b0 "

#25000
b1010000010001000010010011 !
b10100 "

#30000
b10100010101000010010011 !
b101 "

#35000
b1000001100000010101000010010011 !
b11000 "

#40000
b11111111111100010010000010010011 !
b11111111111111111111111111111111 "

#45000
b111111111100010011000010010011 !
b1111111111 "

#50000
b1110100100010000000010000011 !
b11101001 "

#75000
b11111110000100010000110110100011 !
b11111111111111111111111111111011 "

#80000
b1000010001000000100011 !
b0 "

#85000
b110000001010010100100011 !
b1010 "

#110000
b11111110000100001000101011100011 !
b11111111111111111111111111110100 "

#115000
b1000010001010001100011 !
b1000 "

#120000
b1100011100101001100011 !
b10100 "

#125000
b11111110010000100101011011100011 !
b11111111111111111111111111101100 "

#150000
b11111001110111111111000001101111 !
b11111111111111111111111110011100 "

#155000
b111111111000000000000011101111 !
b1111111110 "

#180000
b111111111000101000000011100111 !

#185000
b11000000001000101000000011100111 !
b11111111111111111111110000000010 "

#210000
b1111010000101000110111 !
b1111010000000000000000 "

#215000
b10000000000000000000100110110111 !
b10000000000000000000000000000000 "

#220000
b1111010000101000010111 !
b1111010000000000000000 "

#225000
b10000000000000000000100110010111 !
b10000000000000000000000000000000 "
